adamixture-1.0.1.dist-info/WHEEL
adamixture-1.0.1.dist-info/entry_points.txt
adamixture-1.0.1.dist-info/top_level.txt
adamixture-1.0.1.dist-info/METADATA
adamixture-1.0.1.dist-info/RECORD
adamixture/_version.py
adamixture/entry.py
adamixture/__init__.py
adamixture/model/em_adam.py
adamixture/model/adamixture.py
adamixture/model/__init__.py
adamixture/src/snp_reader.py
adamixture/src/utils.py
adamixture/src/main.py
adamixture/src/svd.py
adamixture/src/evaluation.py
adamixture/src/__init__.py
adamixture/src/utils_c/tools.pyx
adamixture/src/utils_c/tools.c
adamixture/src/utils_c/em.pyx
adamixture/src/utils_c/em.c
adamixture/src/utils_c/rsvd.pyx
adamixture/src/utils_c/rsvd.cpython-312-x86_64-linux-gnu.so
adamixture/src/utils_c/tools.cpython-312-x86_64-linux-gnu.so
adamixture/src/utils_c/rsvd.c
adamixture/src/utils_c/__init__.py
adamixture/src/utils_c/em.cpython-312-x86_64-linux-gnu.so
adamixture.libs/libgomp-a34b3233.so.1.0.0
