Metadata-Version: 2.4
Name: adamixture
Version: 1.0.1
Summary: ADAMIXTURE: Adaptive First-Order Optimization for Biobank-Scale Ancestry Inference
Home-page: https://github.com/AI-sandbox/adamixture
Author: Joan Saurina Ricós
Author-email: joansaurinaricos@gmail.com
License: CC BY-NC 4.0
Classifier: Development Status :: 5 - Production/Stable
Classifier: Intended Audience :: Science/Research
Classifier: Topic :: Scientific/Engineering
Classifier: Programming Language :: Python :: 3.10
Classifier: Programming Language :: Python :: 3.11
Classifier: Programming Language :: Python :: 3.12
Classifier: Operating System :: POSIX :: Linux
Classifier: Operating System :: MacOS
Requires-Python: >=3.10
Requires-Dist: configargparse>=1.5.3
Requires-Dist: Cython>3.0.0
Requires-Dist: numpy>2.0.0
Requires-Dist: setuptools>=61.0
Provides-Extra: testing
Requires-Dist: tox; extra == "testing"
Requires-Dist: pytest; extra == "testing"
Requires-Dist: pytest-cov; extra == "testing"
Requires-Dist: pytest-mock; extra == "testing"
